egtest/__init__.py
egtest/injecthooks.py
egtest/main.py
egtest/parsers.py
egtest/reporters.py
egtest/utils.py
egtest-0.1.0.data/scripts/egtest
egtest-0.1.0.dist-info/dependency_links.txt
egtest-0.1.0.dist-info/DESCRIPTION.rst
egtest-0.1.0.dist-info/entry_points.txt
egtest-0.1.0.dist-info/METADATA
egtest-0.1.0.dist-info/pydist.json
egtest-0.1.0.dist-info/RECORD
egtest-0.1.0.dist-info/top_level.txt
egtest-0.1.0.dist-info/WHEEL
