Metadata-Version: 2.0
Name: egtest
Version: 0.1.0
Summary: Test example code blocks in documentation
Home-page: https://github.com/kimmobrunfeldt/egtest
Author: Kimmo Brunfeldt
Author-email: kimmobrunfeldt@gmail.com
License: MIT
Keywords: egtest test documentation doctest
Platform: UNKNOWN
Classifier: Development Status :: 2 - Pre-Alpha
Classifier: Intended Audience :: Developers
Classifier: License :: OSI Approved :: MIT License
Classifier: Natural Language :: English
Classifier: Programming Language :: Python :: 2
Classifier: Programming Language :: Python :: 2.6
Classifier: Programming Language :: Python :: 2.7
Classifier: Programming Language :: Python :: 3
Classifier: Programming Language :: Python :: 3.3
Classifier: Programming Language :: Python :: Implementation :: PyPy
Requires-Dist: docopt (==0.6.1)
Requires-Dist: docopts (==0.6.1)
Requires-Dist: six (==1.6.1)
Requires-Dist: colorama
